apps/__init__.py
apps/start_detector.py
guardcam/__init__.py
guardcam/detection.py
guardcam/notification.py
guardcam/streaming.py
guardcam-0.2.4.dist-info/METADATA
guardcam-0.2.4.dist-info/WHEEL
guardcam-0.2.4.dist-info/entry_points.txt
guardcam-0.2.4.dist-info/top_level.txt
guardcam-0.2.4.dist-info/RECORD
